arb_logger/__init__.py
arb_logger/alert_message.py
arb_logger/arb_alerts.py
arb_logger/logger.py
arb_logger-2.2.1.dist-info/METADATA
arb_logger-2.2.1.dist-info/WHEEL
arb_logger-2.2.1.dist-info/entry_points.txt
arb_logger-2.2.1.dist-info/top_level.txt
arb_logger-2.2.1.dist-info/RECORD
