Metadata-Version: 2.1
Name: arb_logger
Version: 2.2.1
Summary: A custom logger with Redis integration
Home-page: https://github.com/Acid3croco/arb-trops-services
Author: arb
Author-email: arb.trops@gmail.com
Requires-Dist: coloredlogs
Requires-Dist: redis
Requires-Dist: pync
